box/__init__.py
box/__main__.py
box/cleaner.py
box/cli.py
box/config.py
box/env_vars.py
box/formatters.py
box/initialization.py
box/installer.py
box/packager.py
box/utils.py
box/installer_utils/__init__.py
box/installer_utils/linux_hlp.py
box/installer_utils/mac_hlp.py
box/installer_utils/windows_hlp.py
box_packager-0.4.0.dist-info/METADATA
box_packager-0.4.0.dist-info/WHEEL
box_packager-0.4.0.dist-info/entry_points.txt
box_packager-0.4.0.dist-info/licenses/LICENSE.txt
box_packager-0.4.0.dist-info/RECORD
